README.rst
setup.py
django_lumberjack.egg-info/PKG-INFO
django_lumberjack.egg-info/SOURCES.txt
django_lumberjack.egg-info/dependency_links.txt
django_lumberjack.egg-info/not-zip-safe
django_lumberjack.egg-info/pbr.json
django_lumberjack.egg-info/requires.txt
django_lumberjack.egg-info/top_level.txt
lumberjack/__init__.py
lumberjack/admin.py
lumberjack/handlers.py
lumberjack/models.py
lumberjack/migrations/0001_initial.py
lumberjack/migrations/__init__.py