Metadata-Version: 1.0
Name: django-lumberjack
Version: 0.2.1
Summary: Simple logging. Stored in database, accessed in Django admin.
Home-page: http://github.com/lander2k2/django-lumberjack
Author: Richard Lander
Author-email: lander2k2@gmail.com
License: MIT
Platform: UNKNOWN
